[
  {
    "title": "DUO",
    "category": "メイクアップ",
    "summary": "KPI目標: 2000",
    "content": "① 見出し  \nto buy 実績サマリ  \n再生回数は未入力%で達成、成果検証と次回改善へ  \n\n② 目的  \n商品理解促進とバズ感醸成のため to buy を活用  \n\n③ KPI表  \n┌────────┬──────────┐  \n│ KPI   │ 2000      │  \n│ 実績   │ 未入力    │  \n│ 達成率 │ 未入力%   │  \n└────────┴──────────┘  \n\n④ 指標比較表  \nviews | likes | comments | shares | saves | 6sVR | complVR  \n\n⑤ Worked / Improvements  \n🔴 Worked  \n◎印象的な冒頭コピーで注目引き付け  \n・「こんにちは、皆さん」の冒頭コピーが親近感を生み視聴継続を促進  \n◎実践デモで保存意欲を喚起  \n・リンゴを切る映像と「超リアルな映像を生成できます」の価値提案が記憶に残り保存増を見込  \n◎ブランド認知と差別化を強化  \n・AI超リアル生成を強調する価値提案がブランド想起を促進し波及効果に貢献  \n\n🔵 Improvements  \n◎フック強化で視聴引き上げ余地  \n・開始コピーが一般的なため疑問形や数字訴求を加えて伸びしろ  \n◎CTA導入でコミュニティ施策強化  \n・シェア・保存促進の呼びかけがなく機会損失、明確なCTA追加を推奨\nご確認ください。 <button data-message=\"OK\">OK</button> <button data-message=\"修正\">修正</button> ",
    "conversation_id": "2a9ff799-62d9-44fc-aba7-b89828b537bc",
    "id": 1750822277539,
    "created_at": "2025-06-25T03:31:17.539Z"
  },
  {
    "title": "DUO",
    "category": "メイクアップ",
    "summary": "KPI目標: 2000",
    "content": "① 見出し  \nto buy 実績サマリ  \n再生回数は未入力%で達成、成果検証と次回改善へ  \n\n② 目的  \n商品理解促進とバズ感醸成のため to buy を活用  \n\n③ KPI表  \n┌────────┬──────────┐  \n│ KPI   │ 100       │  \n│ 実績   │ 未入力    │  \n│ 達成率 │ 未入力%   │  \n└────────┴──────────┘  \n\n④ 指標比較表  \nviews | likes | comments | shares | saves | 6sVR | complVR  \n\n⑤ Worked / Improvements  \n🔴 Worked  \n◎ 印象的な冒頭コピーで注目引き付け  \n・「こんにちは、皆さん」の冒頭コピーが親近感を生み視聴継続を促進  \n◎ 実践デモで保存意欲を喚起  \n・リンゴを切る映像と「超リアルな映像を生成できます」の価値提案が記憶に残り保存増を見込  \n◎ ブランド認知と差別化を強化  \n・AI超リアル生成を強調する価値提案がブランド想起を促進し波及効果に貢献  \n\n🔵 Improvements  \n◎ フック強化で視聴引き上げ余地  \n・開始コピーが一般的なため疑問形や数字訴求を加えて伸びしろ  \n◎ CTA導入でコミュニティ施策強化  \n・シェア・保存促進の呼びかけがなく機会損失、明確なCTA追加を推奨ご確認ください。 <button data-message=\"OK\">OK</button> <button data-message=\"修正\">修正</button> ",
    "conversation_id": "2a9ff799-62d9-44fc-aba7-b89828b537bc",
    "id": 1750822297284,
    "created_at": "2025-06-25T03:31:37.284Z"
  }
]